{
  "name": "Cole Castro",
  "age": 43,
  "address": {
    "street": "Fupla Trail",
    "city": "Zodkore",
    "state": "MO",
    "zip": "16653"
  },
  "contact": {
    "phone": "(883) 938-5080",
    "servicePhone": "800627917"
  },
  "birthday": "1981-09-08T06:54:48.970Z",
  "ip": "192.93.168.178",
  "foo": "bar",
  "profile": {
    "about": "Rerlar bil eca usoejeup zohlaret vujuupe caij fopa buptu ke osubaf fi kovpotwew to. Zu epfishij lolwipil man gon sew gezganloj ufutehej uz wihug pazego vo dar ba oto folekcez mi jokfuzo. Kopfuhe wetoepa jam nacle jalijo etkugmu ozru orwomeg moiju wuh kosizbu zi. Bobiv atsitvup wabmitwi culuj migiwi vecib fas wegtebir unu mewolwas hebub kig sos door ti kev. Fi ec nege kosefo tija gis rohefjo zepafi do rahareh afaneho sido lahawzeg gowitki zulerag olabpo. Fa aftifna upi jivav wehnuvfug sazrezvis jeulosaz vuhop inde fobvur jofrulza visok fekacnu halenez nowpok ca cugceten.",
    "bio": "Dede dapnaf zi noga bisjaihu az wagnogeh dacibu ze dopcuhur kogol ejene liga kupurel bub. Geh cezhoboj megsodefe veirole cijsewvaw ferzul ufwit siwzi ovo deslot ugahluw gukse sap. Mekfifat dukmegob wedihow wir atfabbag iza inbobuku rivedow cuzzahcus hahip woweggus vusijzil vowa gompunzul viawi mu. Vaca nancikif jugziw jalovuja veep cam pefoaf boaze mavze dikocjur riowtu idu rurito bup."
  },
  "apiKey": "595c09de5e1f2c9f4ebee1e8e26dcb703f1a1a162966ac3fc32ebe0c03911aaa",
  "currency": {
    "code": "BYR",
    "name": "Belarus Ruble"
  }
}